aurorastack/__init__.py
aurorastack/api/__init__.py
aurorastack/api/core/__init__.py
aurorastack/api/core/v1/__init__.py
aurorastack/api/core/v1/handler_pb2.py
aurorastack/api/core/v1/handler_pb2_grpc.py
aurorastack/api/core/v1/query_pb2.py
aurorastack/api/core/v1/query_pb2_grpc.py
aurorastack/api/core/v1/server_info_pb2.py
aurorastack/api/core/v1/server_info_pb2_grpc.py
aurorastack/api/core/v2/__init__.py
aurorastack/api/core/v2/handler_pb2.py
aurorastack/api/core/v2/handler_pb2_grpc.py
aurorastack/api/core/v2/plugin_pb2.py
aurorastack/api/core/v2/plugin_pb2_grpc.py
aurorastack/api/core/v2/query_pb2.py
aurorastack/api/core/v2/query_pb2_grpc.py
aurorastack/api/sample/__init__.py
aurorastack/api/sample/v1/__init__.py
aurorastack/api/sample/v1/helloworld_pb2.py
aurorastack/api/sample/v1/helloworld_pb2_grpc.py
aurorastack_api-0.1.1.dist-info/METADATA
aurorastack_api-0.1.1.dist-info/WHEEL
aurorastack_api-0.1.1.dist-info/top_level.txt
aurorastack_api-0.1.1.dist-info/RECORD
