Metadata-Version: 2.1
Name: aurorastack-api
Version: 0.1.1
Summary: AuroraStack Core API Protobuf
Home-page: https://aurorastack.io/
Author: AuroraStack
Author-email: admin@aurorastack.io
License: Apache Software License
